Models/__init__.py
Models/constant.py
Models/expression.py
Models/formula.py
Models/function.py
Models/model_types.py
Models/parser.py
Models/range.py
Models/reference.py
Tests/__init__.py
Tests/test_constant.py
Tests/test_expression.py
Tests/test_function.py
Tests/test_parser.py
Tests/test_range.py
Tests/test_reference.py
ExcelFormulaParser-1.0.2.dist-info/LICENSE
ExcelFormulaParser-1.0.2.dist-info/METADATA
ExcelFormulaParser-1.0.2.dist-info/WHEEL
ExcelFormulaParser-1.0.2.dist-info/top_level.txt
ExcelFormulaParser-1.0.2.dist-info/RECORD
