Metadata-Version: 2.1
Name: ExcelFormulaParser
Version: 1.0.2
Summary: A framework to break down Excel Formula strings into a parsable and modifiable JSON data structure.
Home-page: https://github.com/Voltaic314/ExcelFormulaParser
Author: Voltaic314
Author-email: logan@stax.ai
License: UNKNOWN
Platform: UNKNOWN
Classifier: Programming Language :: Python :: 3
Classifier: License :: OSI Approved :: MIT License
Classifier: Operating System :: OS Independent
Requires-Python: >=3.6
License-File: LICENSE
Requires-Dist: openpyxl
Requires-Dist: pandas
